LICENSE
MANIFEST.in
README.md
pyproject.toml
requirements.txt
setup.py
openai_whisper.egg-info/PKG-INFO
openai_whisper.egg-info/SOURCES.txt
openai_whisper.egg-info/dependency_links.txt
openai_whisper.egg-info/entry_points.txt
openai_whisper.egg-info/requires.txt
openai_whisper.egg-info/top_level.txt
whisper/__init__.py
whisper/__main__.py
whisper/audio.py
whisper/decoding.py
whisper/model.py
whisper/timing.py
whisper/tokenizer.py
whisper/transcribe.py
whisper/triton_ops.py
whisper/utils.py
whisper/version.py
whisper/assets/mel_filters.npz
whisper/assets/gpt2/merges.txt
whisper/assets/gpt2/special_tokens_map.json
whisper/assets/gpt2/tokenizer_config.json
whisper/assets/gpt2/vocab.json
whisper/assets/multilingual/added_tokens.json
whisper/assets/multilingual/merges.txt
whisper/assets/multilingual/special_tokens_map.json
whisper/assets/multilingual/tokenizer_config.json
whisper/assets/multilingual/vocab.json
whisper/normalizers/__init__.py
whisper/normalizers/basic.py
whisper/normalizers/english.json
whisper/normalizers/english.py