Metadata-Version: 2.1
Name: openai-whisper
Version: 20230307
Summary: Robust Speech Recognition via Large-Scale Weak Supervision
Home-page: https://github.com/openai/whisper
Author: OpenAI
License: MIT
Platform: UNKNOWN
Requires-Python: >=3.8
Provides-Extra: dev
